LICENSE
README.md
setup.py
colorless/__init__.py
colorless.egg-info/PKG-INFO
colorless.egg-info/SOURCES.txt
colorless.egg-info/dependency_links.txt
colorless.egg-info/top_level.txt