Metadata-Version: 2.1
Name: colorless
Version: 0.0.1
Summary: Colorless green ideas sleep furiously
Home-page: https://github.com/alvations/colorless
Author: 
License: UNKNOWN
Platform: UNKNOWN
Classifier: Programming Language :: Python :: 3
Classifier: License :: OSI Approved :: MIT License
Classifier: Operating System :: OS Independent
License-File: LICENSE
